{
  "collapse-filter": false,
  "search": "",
  "showTags": true,
  "showAttachments": false,
  "hideUnresolved": false,
  "showOrphans": true,
  "collapse-color-groups": false,
  "colorGroups": [
    {
      "query": "tag:#documentation  ",
      "color": {
        "a": 1,
        "rgb": 10179925
      }
    },
    {
      "query": "tag:#filosofía  ",
      "color": {
        "a": 1,
        "rgb": 14725458
      }
    },
    {
      "query": "tag:#JavaScript  ",
      "color": {
        "a": 1,
        "rgb": 12748531
      }
    },
    {
      "query": "tag:#tecnica  ",
      "color": {
        "a": 1,
        "rgb": 1506992
      }
    },
    {
      "query": "tag:#Theme-Basics  ",
      "color": {
        "a": 1,
        "rgb": 38128
      }
    },
    {
      "query": "tag:#Code ",
      "color": {
        "a": 1,
        "rgb": 11903989
      }
    },
    {
      "query": "path:\"004 - Notes/AA1 - Code\"  ",
      "color": {
        "a": 1,
        "rgb": 8016364
      }
    }
  ],
  "collapse-display": false,
  "showArrow": false,
  "textFadeMultiplier": 0.3,
  "nodeSizeMultiplier": 0.916666666666667,
  "lineSizeMultiplier": 1.68229166666667,
  "collapse-forces": false,
  "centerStrength": 0.518713248970312,
  "repelStrength": 10,
  "linkStrength": 1,
  "linkDistance": 250,
  "scale": 0.4444444444444444,
  "close": false
}